README.rst
setup.py
classowl_client/__init__.py
classowl_client/client.py
classowl_client/serializer.py
classowl_client/shortcuts.py
classowl_client.egg-info/PKG-INFO
classowl_client.egg-info/SOURCES.txt
classowl_client.egg-info/dependency_links.txt
classowl_client.egg-info/requires.txt
classowl_client.egg-info/top_level.txt