Metadata-Version: 1.1
Name: classowl-client
Version: 0.1a2
Summary: a client for the classowl.com REST API
Home-page: http://localhost
Author: Matei Trusca
Author-email: matei.trusca@devlabel.com
License: LICENSE
Platform: UNKNOWN
Classifier: Programming Language :: Python :: 2.7
Classifier: License :: OSI Approved :: MIT License
Classifier: Intended Audience :: Developers
Classifier: Topic :: Internet :: WWW/HTTP
